fd_auto_compress/__init__.py
fd_auto_compress/dataset.py
fd_auto_compress/fd_auto_compress.py
fd_auto_compress-0.0.1.dist-info/METADATA
fd_auto_compress-0.0.1.dist-info/WHEEL
fd_auto_compress-0.0.1.dist-info/top_level.txt
fd_auto_compress-0.0.1.dist-info/RECORD
