Metadata-Version: 2.1
Name: fd-auto-compress
Version: 0.0.1
Summary: A toolkit for model auto compression of FastDeploy.
Home-page: https://github.com/PaddlePaddle/FastDeploy.git
Author: fastdeploy
Author-email: fastdeploy@baidu.com
License: Apache 2.0
Classifier: Programming Language :: Python :: 3
Classifier: License :: OSI Approved :: Apache Software License
Classifier: Operating System :: OS Independent
